redes/__init__.py
redes/core.py
redes/main.py
redes-0.1.dist-info/METADATA
redes-0.1.dist-info/WHEEL
redes-0.1.dist-info/entry_points.txt
redes-0.1.dist-info/top_level.txt
redes-0.1.dist-info/RECORD
