Metadata-Version: 2.1
Name: redes
Version: 0.1
Summary: get redes
Home-page: UNKNOWN
Author: DanteOnline
Author-email: iamdanteonline@gmail.com
License: GNU General Public License v3.0
Keywords: rede
Platform: UNKNOWN
